{
  "miniprogramRoot": "dist/",
  "projectname": "SH",
  "description": "taro",
  "appid": "wx723459ef9c3af178",
  "setting": {
    "urlCheck": false,
    "es6": true,
    "enhance": true,
    "postcss": true,
    "preloadBackgroundData": false,
    "minified": true,
    "newFeature": false,
    "coverView": true,
    "nodeModules": true,
    "autoAudits": false,
    "showShadowRootInWxmlPanel": true,
    "scopeDataCheck": false,
    "uglifyFileName": false,
    "checkInvalidKey": true,
    "checkSiteMap": false,
    "uploadWithSourceMap": true,
    "compileHotReLoad": false,
    "lazyloadPlaceholderEnable": false,
    "useMultiFrameRuntime": false,
    "useApiHook": false,
    "useApiHostProcess": false,
    "babelSetting": {
      "ignore": [],
      "disablePlugins": [],
      "outputPath": ""
    },
    "enableEngineNative": false,
    "useIsolateContext": true,
    "userConfirmedBundleSwitch": false,
    "packNpmManually": true,
    "packNpmRelationList": [
      {
        "packageJsonPath": "./package.json",
        "miniprogramNpmDistDir": "./"
      }
    ],
    "minifyWXSS": true,
    "showES6CompileOption": false
  },
  "packOptions": {
    "ignore": []
  },
  "compileType": "miniprogram",
  "libVersion": "2.25.4",
  "simulatorType": "wechat",
  "simulatorPluginLibVersion": {},
  "condition": {}
}